{
  "project_info": {
    "project_number": "653355816857",
    "project_id": "b-s-pavz",
    "storage_bucket": "b-s-pavz.appspot.com"
  },
  "client": [
    {
      "client_info": {
        "mobilesdk_app_id": "1:653355816857:android:06ea7ca2468e8aeba22508",
        "android_client_info": {
          "package_name": "com.example.pavzapplication"
        }
      },
      "oauth_client": [
        {
          "client_id": "653355816857-tqoql4cnfm8hv9jklf95rc2pirbo26p6.apps.googleusercontent.com",
          "client_type": 3
        }
      ],
      "api_key": [
        {
          "current_key": "AIzaSyCvHp2zoUG9ILv0IuhmCHxZq7AE_E6CgJ4"
        }
      ],
      "services": {
        "appinvite_service": {
          "other_platform_oauth_client": [
            {
              "client_id": "653355816857-tqoql4cnfm8hv9jklf95rc2pirbo26p6.apps.googleusercontent.com",
              "client_type": 3
            }
          ]
        }
      }
    }
  ],
  "configuration_version": "1"
}